django_post_api/__init__.py
django_post_api/apps.py
django_post_api/constants.py
django_post_api/doc.py
django_post_api/enums.py
django_post_api/errors.py
django_post_api/fields.py
django_post_api/helpers.py
django_post_api/models.py
django_post_api/params.py
django_post_api/views.py
django_post_api/management/__init__.py
django_post_api/management/commands/__init__.py
django_post_api/management/commands/showdoc.py
django_post_api/middlewares/__init__.py
django_post_api/middlewares/cors.py
django_post_api/middlewares/error.py
django_post_api/migrations/__init__.py
django_post_api-1.1.7.dist-info/LICENSE
django_post_api-1.1.7.dist-info/METADATA
django_post_api-1.1.7.dist-info/WHEEL
django_post_api-1.1.7.dist-info/top_level.txt
django_post_api-1.1.7.dist-info/RECORD
