Metadata-Version: 2.1
Name: django-post-api
Version: 1.1.7
Summary: Django Post API
Home-page: https://gitee.com/songhaoi/django-post-api
Author: songhaoi
Author-email: songhao2020@hotmail.com
Classifier: Framework :: Django
Classifier: Programming Language :: Python :: 3
Classifier: License :: OSI Approved :: MIT License
Classifier: Operating System :: OS Independent
Requires-Python: >=3.10
License-File: LICENSE
Requires-Dist: Django (>=4.2)
Requires-Dist: requests (>=2.32.3)
